psychopy_labjack/__init__.py
psychopy_labjack/labjacks.py
psychopy_labjack-0.0.1.dist-info/LICENSE
psychopy_labjack-0.0.1.dist-info/METADATA
psychopy_labjack-0.0.1.dist-info/WHEEL
psychopy_labjack-0.0.1.dist-info/top_level.txt
psychopy_labjack-0.0.1.dist-info/RECORD
